[
  {
    "cardName": "Gold Delta",
    "issuerName": "Amex",
    "rewardProvider": "Delta",
    "curBonusPts": 30000,
    "centValueOfPoint": 1.25,
    "curBonusVal": 375,
    "otherPerks": "0",
    "minSpendVal": 1000,
    "minSpendMonths": 3,
    "annualFee": 95,
    "annualFeeWaived": true,
    "personalOrBiz": "Personal",
    "ftf": 0,
    "useOnCt": "Yes",
    "curBonusPrctl": 35,
    "minSpendPrctl": 71,
    "annualFeePrctl": 90,
    "overallRank": 99,
    "cardKey": "amex_per_gold_delta"
  },
  {
    "cardName": "Starwood Preferred Guest",
    "issuerName": "Amex",
    "rewardProvider": "SPG",
    "curBonusPts": 25000,
    "centValueOfPoint": 2.35,
    "curBonusVal": 587.5,
    "otherPerks": "0",
    "minSpendVal": 3000,
    "minSpendMonths": 3,
    "annualFee": 95,
    "annualFeeWaived": true,
    "personalOrBiz": "Personal",
    "ftf": 0,
    "useOnCt": "Yes",
    "curBonusPrctl": 55,
    "minSpendPrctl": 14,
    "annualFeePrctl": 90,
    "overallRank": 96,
    "cardKey": "amex_per_starwood_preferred_guest"
  },
  {
    "cardName": "Platinum",
    "issuerName": "Amex",
    "rewardProvider": "MR",
    "curBonusPts": 40000,
    "centValueOfPoint": 1.8,
    "curBonusVal": 720,
    "otherPerks": "$200 Airline Credit + $100 Global Entry",
    "minSpendVal": 3000,
    "minSpendMonths": 3,
    "annualFee": 450,
    "annualFeeWaived": false,
    "personalOrBiz": "Personal",
    "ftf": 0,
    "useOnCt": "Yes",
    "curBonusPrctl": 67,
    "minSpendPrctl": 14,
    "annualFeePrctl": 5,
    "overallRank": 75,
    "cardKey": "amex_per_platinum"
  },
  {
    "cardName": "Mercedes-Benz Platinum",
    "issuerName": "Amex",
    "rewardProvider": "MR",
    "curBonusPts": 75000,
    "centValueOfPoint": 1.8,
    "curBonusVal": 1350,
    "otherPerks": "0",
    "minSpendVal": 3000,
    "minSpendMonths": 3,
    "annualFee": 475,
    "annualFeeWaived": false,
    "personalOrBiz": "Personal",
    "ftf": 0,
    "useOnCt": "Yes",
    "curBonusPrctl": 100,
    "minSpendPrctl": 14,
    "annualFeePrctl": 0,
    "overallRank": 106,
    "cardKey": "amex_per_mercedes-benz_platinum"
  },
  {
    "cardName": "Premier Rewards Gold",
    "issuerName": "Amex",
    "rewardProvider": "MR",
    "curBonusPts": 40000,
    "centValueOfPoint": 1.8,
    "curBonusVal": 720,
    "otherPerks": "$100 Airline Credit",
    "minSpendVal": 1000,
    "minSpendMonths": 3,
    "annualFee": 195,
    "annualFeeWaived": true,
    "personalOrBiz": "Personal",
    "ftf": 0,
    "useOnCt": "Yes",
    "curBonusPrctl": 67,
    "minSpendPrctl": 71,
    "annualFeePrctl": 79,
    "overallRank": 127,
    "cardKey": "amex_per_premier_rewards_gold"
  },
  {
    "cardName": "Alaska",
    "issuerName": "Bank of America",
    "rewardProvider": "Alaska",
    "curBonusPts": 25000,
    "centValueOfPoint": 1.8,
    "curBonusVal": 450,
    "otherPerks": "$100 + Companion Pass",
    "minSpendVal": 1000,
    "minSpendMonths": 3,
    "annualFee": 75,
    "annualFeeWaived": false,
    "personalOrBiz": "Personal",
    "ftf": 0.03,
    "useOnCt": "Yes",
    "curBonusPrctl": 42,
    "minSpendPrctl": 71,
    "annualFeePrctl": 84,
    "overallRank": 104,
    "cardKey": "boa_per_alaska"
  },
  {
    "cardName": "Virgin Atlantic",
    "issuerName": "Bank of America",
    "rewardProvider": "Virgin Atlantic",
    "curBonusPts": 20000,
    "centValueOfPoint": 1.5,
    "curBonusVal": 300,
    "otherPerks": "0",
    "minSpendVal": 1,
    "minSpendMonths": 6,
    "annualFee": 90,
    "annualFeeWaived": false,
    "personalOrBiz": "Personal",
    "ftf": 0.01,
    "useOnCt": "Yes",
    "curBonusPrctl": 28,
    "minSpendPrctl": 100,
    "annualFeePrctl": 81,
    "overallRank": 100,
    "cardKey": "boa_per_virgin_atlantic"
  },
  {
    "cardName": "JetBlue Plus",
    "issuerName": "Barclays",
    "rewardProvider": "JetBlue",
    "curBonusPts": 30000,
    "centValueOfPoint": 1.25,
    "curBonusVal": 375,
    "otherPerks": "5,000 anniversary bonus",
    "minSpendVal": 1000,
    "minSpendMonths": 3,
    "annualFee": 99,
    "annualFeeWaived": false,
    "personalOrBiz": "Personal",
    "ftf": 0,
    "useOnCt": "Yes",
    "curBonusPrctl": 35,
    "minSpendPrctl": 71,
    "annualFeePrctl": 79,
    "overallRank": 95,
    "cardKey": "barc_per_jetblue_plus"
  },
  {
    "cardName": "Frontier",
    "issuerName": "Barclays",
    "rewardProvider": "Frontier",
    "curBonusPts": 40000,
    "centValueOfPoint": 1.1,
    "curBonusVal": 440,
    "otherPerks": "0",
    "minSpendVal": 500,
    "minSpendMonths": 3,
    "annualFee": 69,
    "annualFeeWaived": false,
    "personalOrBiz": "Personal",
    "ftf": 0.03,
    "useOnCt": "Yes",
    "curBonusPrctl": 41,
    "minSpendPrctl": 86,
    "annualFeePrctl": 85,
    "overallRank": 109,
    "cardKey": "barc_per_frontier"
  },
  {
    "cardName": "Arrival +",
    "issuerName": "Barclays",
    "rewardProvider": "Arrival",
    "curBonusPts": 40000,
    "centValueOfPoint": 1.02,
    "curBonusVal": 410,
    "otherPerks": "0",
    "minSpendVal": 3000,
    "minSpendMonths": 3,
    "annualFee": 89,
    "annualFeeWaived": true,
    "personalOrBiz": "Personal",
    "ftf": 0,
    "useOnCt": "Yes",
    "curBonusPrctl": 38,
    "minSpendPrctl": 14,
    "annualFeePrctl": 91,
    "overallRank": 80,
    "cardKey": "barc_per_arrival_+"
  },
  {
    "cardName": "Lufthansa",
    "issuerName": "Barclays",
    "rewardProvider": "Miles & More",
    "curBonusPts": 50000,
    "centValueOfPoint": 1.4,
    "curBonusVal": 700,
    "otherPerks": "0",
    "minSpendVal": 5000,
    "minSpendMonths": 0,
    "annualFee": 79,
    "annualFeeWaived": false,
    "personalOrBiz": "Personal",
    "ftf": 0,
    "useOnCt": "Yes",
    "curBonusPrctl": 65,
    "minSpendPrctl": 0,
    "annualFeePrctl": 83,
    "overallRank": 98,
    "cardKey": "barc_per_lufthansa"
  },
  {
    "cardName": "Hawaiian",
    "issuerName": "Barclays",
    "rewardProvider": "Hawaiian",
    "curBonusPts": 35000,
    "centValueOfPoint": 1.2,
    "curBonusVal": 420,
    "otherPerks": "0",
    "minSpendVal": 1000,
    "minSpendMonths": 3,
    "annualFee": 89,
    "annualFeeWaived": false,
    "personalOrBiz": "Personal",
    "ftf": 0,
    "useOnCt": "Yes",
    "curBonusPrctl": 39,
    "minSpendPrctl": 71,
    "annualFeePrctl": 81,
    "overallRank": 100,
    "cardKey": "barc_per_hawaiian"
  },
  {
    "cardName": "Venture One Rewards",
    "issuerName": "Capital One",
    "rewardProvider": "Venture",
    "curBonusPts": 20000,
    "centValueOfPoint": 1,
    "curBonusVal": 200,
    "otherPerks": "0",
    "minSpendVal": 1000,
    "minSpendMonths": 3,
    "annualFee": 0,
    "annualFeeWaived": "",
    "personalOrBiz": "Personal",
    "ftf": 0,
    "useOnCt": "Yes",
    "curBonusPrctl": 19,
    "minSpendPrctl": 71,
    "annualFeePrctl": 100,
    "overallRank": 87,
    "cardKey": "capital_one_per_venture_one_rewards"
  },
  {
    "cardName": "Venture Rewards",
    "issuerName": "Capital One",
    "rewardProvider": "Venture",
    "curBonusPts": 40000,
    "centValueOfPoint": 1,
    "curBonusVal": 400,
    "otherPerks": "0",
    "minSpendVal": 3000,
    "minSpendMonths": 3,
    "annualFee": 59,
    "annualFeeWaived": true,
    "personalOrBiz": "Personal",
    "ftf": 0,
    "useOnCt": "Yes",
    "curBonusPrctl": 37,
    "minSpendPrctl": 14,
    "annualFeePrctl": 94,
    "overallRank": 80,
    "cardKey": "capital_one_per_venture_rewards"
  },
  {
    "cardName": "Freedom Unlimited",
    "issuerName": "Chase",
    "rewardProvider": "UR",
    "curBonusPts": 15000,
    "centValueOfPoint": 1.9,
    "curBonusVal": 285,
    "otherPerks": "0",
    "minSpendVal": 500,
    "minSpendMonths": 3,
    "annualFee": 0,
    "annualFeeWaived": "",
    "personalOrBiz": "Personal",
    "ftf": 0.03,
    "useOnCt": "Yes",
    "curBonusPrctl": 27,
    "minSpendPrctl": 86,
    "annualFeePrctl": 100,
    "overallRank": 101,
    "cardKey": "chase_per_freedom_unlimited"
  },
  {
    "cardName": "United Explorer",
    "issuerName": "Chase",
    "rewardProvider": "United",
    "curBonusPts": 35000,
    "centValueOfPoint": 1.45,
    "curBonusVal": 507.5,
    "otherPerks": "0",
    "minSpendVal": 2000,
    "minSpendMonths": 3,
    "annualFee": 95,
    "annualFeeWaived": true,
    "personalOrBiz": "Personal",
    "ftf": 0,
    "useOnCt": "Yes",
    "curBonusPrctl": 47,
    "minSpendPrctl": 43,
    "annualFeePrctl": 90,
    "overallRank": 100,
    "cardKey": "chase_per_united_explorer"
  },
  {
    "cardName": "Freedom",
    "issuerName": "Chase",
    "rewardProvider": "UR",
    "curBonusPts": 15000,
    "centValueOfPoint": 1.9,
    "curBonusVal": 285,
    "otherPerks": "0",
    "minSpendVal": 500,
    "minSpendMonths": 3,
    "annualFee": 0,
    "annualFeeWaived": "",
    "personalOrBiz": "Personal",
    "ftf": 0.03,
    "useOnCt": "Yes",
    "curBonusPrctl": 27,
    "minSpendPrctl": 86,
    "annualFeePrctl": 100,
    "overallRank": 101,
    "cardKey": "chase_per_freedom"
  },
  {
    "cardName": "Southwest Plus",
    "issuerName": "Chase",
    "rewardProvider": "Southwest",
    "curBonusPts": 50000,
    "centValueOfPoint": 1.45,
    "curBonusVal": 725,
    "otherPerks": "0",
    "minSpendVal": 2000,
    "minSpendMonths": 3,
    "annualFee": 69,
    "annualFeeWaived": false,
    "personalOrBiz": "Personal",
    "ftf": 0.03,
    "useOnCt": "Yes",
    "curBonusPrctl": 67,
    "minSpendPrctl": 43,
    "annualFeePrctl": 85,
    "overallRank": 119,
    "cardKey": "chase_per_southwest_plus"
  },
  {
    "cardName": "British Airways",
    "issuerName": "Chase",
    "rewardProvider": "Avios",
    "curBonusPts": 50000,
    "centValueOfPoint": 1.4,
    "curBonusVal": 700,
    "otherPerks": "0",
    "minSpendVal": 2000,
    "minSpendMonths": 3,
    "annualFee": 95,
    "annualFeeWaived": true,
    "personalOrBiz": "Personal",
    "ftf": 0,
    "useOnCt": "Yes",
    "curBonusPrctl": 65,
    "minSpendPrctl": 43,
    "annualFeePrctl": 90,
    "overallRank": 118,
    "cardKey": "chase_per_british_airways"
  },
  {
    "cardName": "Southwest Premier",
    "issuerName": "Chase",
    "rewardProvider": "Southwest",
    "curBonusPts": 50000,
    "centValueOfPoint": 1.45,
    "curBonusVal": 725,
    "otherPerks": "0",
    "minSpendVal": 2000,
    "minSpendMonths": 3,
    "annualFee": 99,
    "annualFeeWaived": false,
    "personalOrBiz": "Personal",
    "ftf": 0,
    "useOnCt": "Yes",
    "curBonusPrctl": 67,
    "minSpendPrctl": 43,
    "annualFeePrctl": 79,
    "overallRank": 116,
    "cardKey": "chase_per_southwest_premier"
  },
  {
    "cardName": "Sapphire Preferred",
    "issuerName": "Chase",
    "rewardProvider": "UR",
    "curBonusPts": 55000,
    "centValueOfPoint": 1.9,
    "curBonusVal": 1045,
    "otherPerks": "0",
    "minSpendVal": 4000,
    "minSpendMonths": 3,
    "annualFee": 95,
    "annualFeeWaived": true,
    "personalOrBiz": "Personal",
    "ftf": 0,
    "useOnCt": "Yes",
    "curBonusPrctl": 97,
    "minSpendPrctl": 0,
    "annualFeePrctl": 90,
    "overallRank": 133,
    "cardKey": "chase_per_sapphire_preferred"
  },
  {
    "cardName": "ThankYou Premier",
    "issuerName": "Citi",
    "rewardProvider": "TYP",
    "curBonusPts": 40000,
    "centValueOfPoint": 1.65,
    "curBonusVal": 660,
    "otherPerks": "0",
    "minSpendVal": 3000,
    "minSpendMonths": 3,
    "annualFee": 95,
    "annualFeeWaived": true,
    "personalOrBiz": "Personal",
    "ftf": 0,
    "useOnCt": "Yes",
    "curBonusPrctl": 61,
    "minSpendPrctl": 14,
    "annualFeePrctl": 90,
    "overallRank": 103,
    "cardKey": "citi_per_thankyou_premier"
  },
  {
    "cardName": "AAdvantage Executive",
    "issuerName": "Citi",
    "rewardProvider": "AA",
    "curBonusPts": 50000,
    "centValueOfPoint": 1.5,
    "curBonusVal": 750,
    "otherPerks": "$100 Global Entry",
    "minSpendVal": 5000,
    "minSpendMonths": 3,
    "annualFee": 450,
    "annualFeeWaived": false,
    "personalOrBiz": "Personal",
    "ftf": 0,
    "useOnCt": "Yes",
    "curBonusPrctl": 70,
    "minSpendPrctl": 0,
    "annualFeePrctl": 5,
    "overallRank": 72,
    "cardKey": "citi_per_aadvantage_executive"
  },
  {
    "cardName": "AAdvantage Platinum",
    "issuerName": "Citi",
    "rewardProvider": "AA",
    "curBonusPts": 50000,
    "centValueOfPoint": 1.5,
    "curBonusVal": 750,
    "otherPerks": "0",
    "minSpendVal": 3000,
    "minSpendMonths": 3,
    "annualFee": 95,
    "annualFeeWaived": true,
    "personalOrBiz": "Personal",
    "ftf": 0.03,
    "useOnCt": "Yes",
    "curBonusPrctl": 70,
    "minSpendPrctl": 14,
    "annualFeePrctl": 90,
    "overallRank": 111,
    "cardKey": "citi_per_aadvantage_platinum"
  },
  {
    "cardName": "Prestige",
    "issuerName": "Citi",
    "rewardProvider": "TYP",
    "curBonusPts": 50000,
    "centValueOfPoint": 1.65,
    "curBonusVal": 825,
    "otherPerks": "$250 flight reimbursement + $100 Global Entry",
    "minSpendVal": 2000,
    "minSpendMonths": 3,
    "annualFee": 450,
    "annualFeeWaived": false,
    "personalOrBiz": "Personal",
    "ftf": 0,
    "useOnCt": "Yes",
    "curBonusPrctl": 77,
    "minSpendPrctl": 43,
    "annualFeePrctl": 5,
    "overallRank": 96,
    "cardKey": "citi_per_prestige"
  },
  {
    "cardName": "FlexPerks Select+ (Amex)",
    "issuerName": "US Bank",
    "rewardProvider": "FlexPerks",
    "curBonusPts": 10000,
    "centValueOfPoint": 1.66,
    "curBonusVal": 166,
    "otherPerks": "0",
    "minSpendVal": 1000,
    "minSpendMonths": 4,
    "annualFee": 0,
    "annualFeeWaived": "",
    "personalOrBiz": "Personal",
    "ftf": 0.03,
    "useOnCt": "Yes",
    "curBonusPrctl": 15,
    "minSpendPrctl": 71,
    "annualFeePrctl": 100,
    "overallRank": 84,
    "cardKey": "us_bank_per_flexperks_select+_(amex)"
  },
  {
    "cardName": "Sapphire Reserve",
    "issuerName": "Chase",
    "rewardProvider": "UR",
    "curBonusPts": 100000,
    "centValueOfPoint": 1.9,
    "curBonusVal": 1900,
    "otherPerks": "0",
    "minSpendVal": 4000,
    "minSpendMonths": 3,
    "annualFee": 450,
    "annualFeeWaived": false,
    "personalOrBiz": "Personal",
    "ftf": 0,
    "useOnCt": "Yes",
    "curBonusPrctl": 100,
    "minSpendPrctl": 0,
    "annualFeePrctl": 5,
    "overallRank": 102,
    "cardKey": "chase_per_sapphire_reserve"
  }
]